gpu_utilities/__init__.py
gpu_utilities/errors.py
gpu_utilities/gpu.py
gpu_utilities/gpu_info_obtainer.py
gpu_utilities/gpu_selector.py
gpu_utilities/obtainers/__init__.py
gpu_utilities/obtainers/nvml.py
gpu_utilities/obtainers/torch.py
gpu_utilities/utils/__init__.py
gpu_utilities/utils/bytes.py
gpu_utilities-0.3.0.dist-info/LICENSE
gpu_utilities-0.3.0.dist-info/METADATA
gpu_utilities-0.3.0.dist-info/WHEEL
gpu_utilities-0.3.0.dist-info/top_level.txt
gpu_utilities-0.3.0.dist-info/RECORD
